pkgparser/__init__.py
pkgparser/configuration.py
pkgparser/bin/__init__.py
pkgparser/bin/generate_package_docs.py
pkgparser/bin/parameters.py
pkgparser/bin/parse_docs.py
pkgparser/bin/tester.py
pkgparser/pypackage/__init__.py
pkgparser/pypackage/docstring.py
pkgparser/pypackage/pyclass.py
pkgparser/pypackage/pyfunction.py
pkgparser/pypackage/pyobject.py
pkgparser/pypackage/pypackage.py
pkgparser/utilities/__init__.py
pkgparser/utilities/package.py
pkgparser-1.0.0.dist-info/LICENSE
pkgparser-1.0.0.dist-info/METADATA
pkgparser-1.0.0.dist-info/WHEEL
pkgparser-1.0.0.dist-info/entry_points.txt
pkgparser-1.0.0.dist-info/top_level.txt
pkgparser-1.0.0.dist-info/RECORD
