Metadata-Version: 2.1
Name: pkgparser
Version: 1.0.0
Summary: Python package for parsing metadata from classes and functions in a python package.
Home-page: https://gitlab.com/lgensinger/pkgparser
License: MIT
License-File: LICENSE
Provides-Extra: render
Requires-Dist: mkdpdf (==0.2.1) ; extra == 'render'
Provides-Extra: test
Requires-Dist: mkdpdf ; extra == 'test'
Requires-Dist: pytest ; extra == 'test'
Requires-Dist: pytest-cov ; extra == 'test'
